{
	"configurations" : 
	[
		{
			"directories" : 
			[
				{
					"build" : ".",
					"childIndexes" : 
					[
						1,
						4
					],
					"hasInstallRule" : true,
					"minimumCMakeVersion" : 
					{
						"string" : "3.0.2"
					},
					"projectIndex" : 0,
					"source" : ".",
					"targetIndexes" : 
					[
						0,
						1,
						2,
						18,
						25
					]
				},
				{
					"build" : "gtest",
					"childIndexes" : 
					[
						2
					],
					"minimumCMakeVersion" : 
					{
						"string" : "2.8.8"
					},
					"parentIndex" : 0,
					"projectIndex" : 1,
					"source" : "/usr/src/googletest"
				},
				{
					"build" : "gtest/googlemock",
					"childIndexes" : 
					[
						3
					],
					"minimumCMakeVersion" : 
					{
						"string" : "2.6.4"
					},
					"parentIndex" : 1,
					"projectIndex" : 2,
					"source" : "/usr/src/googletest/googlemock",
					"targetIndexes" : 
					[
						3,
						4
					]
				},
				{
					"build" : "gtest/googletest",
					"minimumCMakeVersion" : 
					{
						"string" : "2.6.4"
					},
					"parentIndex" : 2,
					"projectIndex" : 3,
					"source" : "/usr/src/googletest/googletest",
					"targetIndexes" : 
					[
						5,
						6
					]
				},
				{
					"build" : "plumbing_pub_sub",
					"hasInstallRule" : true,
					"minimumCMakeVersion" : 
					{
						"string" : "3.0.2"
					},
					"parentIndex" : 0,
					"projectIndex" : 4,
					"source" : "plumbing_pub_sub",
					"targetIndexes" : 
					[
						7,
						8,
						9,
						10,
						11,
						12,
						13,
						14,
						15,
						16,
						17,
						19,
						20,
						21,
						22,
						23,
						24
					]
				}
			],
			"name" : "Debug",
			"projects" : 
			[
				{
					"childIndexes" : 
					[
						1,
						4
					],
					"directoryIndexes" : 
					[
						0
					],
					"name" : "Project",
					"targetIndexes" : 
					[
						0,
						1,
						2,
						18,
						25
					]
				},
				{
					"childIndexes" : 
					[
						2
					],
					"directoryIndexes" : 
					[
						1
					],
					"name" : "googletest-distribution",
					"parentIndex" : 0
				},
				{
					"childIndexes" : 
					[
						3
					],
					"directoryIndexes" : 
					[
						2
					],
					"name" : "gmock",
					"parentIndex" : 1,
					"targetIndexes" : 
					[
						3,
						4
					]
				},
				{
					"directoryIndexes" : 
					[
						3
					],
					"name" : "gtest",
					"parentIndex" : 2,
					"targetIndexes" : 
					[
						5,
						6
					]
				},
				{
					"directoryIndexes" : 
					[
						4
					],
					"name" : "plumbing_pub_sub",
					"parentIndex" : 0,
					"targetIndexes" : 
					[
						7,
						8,
						9,
						10,
						11,
						12,
						13,
						14,
						15,
						16,
						17,
						19,
						20,
						21,
						22,
						23,
						24
					]
				}
			],
			"targets" : 
			[
				{
					"directoryIndex" : 0,
					"id" : "clean_test_results::@6890427a1f51a3e7e1df",
					"jsonFile" : "target-clean_test_results-Debug-0c2d8f4834861a8f9446.json",
					"name" : "clean_test_results",
					"projectIndex" : 0
				},
				{
					"directoryIndex" : 0,
					"id" : "download_extra_data::@6890427a1f51a3e7e1df",
					"jsonFile" : "target-download_extra_data-Debug-26d419a6bf2b582c2a72.json",
					"name" : "download_extra_data",
					"projectIndex" : 0
				},
				{
					"directoryIndex" : 0,
					"id" : "doxygen::@6890427a1f51a3e7e1df",
					"jsonFile" : "target-doxygen-Debug-88595cbda2a15872d775.json",
					"name" : "doxygen",
					"projectIndex" : 0
				},
				{
					"directoryIndex" : 2,
					"id" : "gmock::@e3f94eedc5dc07131386",
					"jsonFile" : "target-gmock-Debug-c81db1a6b2551726107a.json",
					"name" : "gmock",
					"projectIndex" : 2
				},
				{
					"directoryIndex" : 2,
					"id" : "gmock_main::@e3f94eedc5dc07131386",
					"jsonFile" : "target-gmock_main-Debug-1c0a87f9361976bd6d7d.json",
					"name" : "gmock_main",
					"projectIndex" : 2
				},
				{
					"directoryIndex" : 3,
					"id" : "gtest::@b738d542747fbb7ea6e3",
					"jsonFile" : "target-gtest-Debug-d898f45654e826fa9517.json",
					"name" : "gtest",
					"projectIndex" : 3
				},
				{
					"directoryIndex" : 3,
					"id" : "gtest_main::@b738d542747fbb7ea6e3",
					"jsonFile" : "target-gtest_main-Debug-eae55c96a49c0280bd01.json",
					"name" : "gtest_main",
					"projectIndex" : 3
				},
				{
					"directoryIndex" : 4,
					"id" : "pub_01_c::@c6794076fdc14014b7f0",
					"jsonFile" : "target-pub_01_c-Debug-ef3785f865e694552fc8.json",
					"name" : "pub_01_c",
					"projectIndex" : 4
				},
				{
					"directoryIndex" : 4,
					"id" : "roscpp_generate_messages_cpp::@c6794076fdc14014b7f0",
					"jsonFile" : "target-roscpp_generate_messages_cpp-Debug-23c221d6a5030deb93ae.json",
					"name" : "roscpp_generate_messages_cpp",
					"projectIndex" : 4
				},
				{
					"directoryIndex" : 4,
					"id" : "roscpp_generate_messages_eus::@c6794076fdc14014b7f0",
					"jsonFile" : "target-roscpp_generate_messages_eus-Debug-f7fb84aba35c7b37650f.json",
					"name" : "roscpp_generate_messages_eus",
					"projectIndex" : 4
				},
				{
					"directoryIndex" : 4,
					"id" : "roscpp_generate_messages_lisp::@c6794076fdc14014b7f0",
					"jsonFile" : "target-roscpp_generate_messages_lisp-Debug-39692e394bebb4eaed37.json",
					"name" : "roscpp_generate_messages_lisp",
					"projectIndex" : 4
				},
				{
					"directoryIndex" : 4,
					"id" : "roscpp_generate_messages_nodejs::@c6794076fdc14014b7f0",
					"jsonFile" : "target-roscpp_generate_messages_nodejs-Debug-a7d0e53e7deb8a895e45.json",
					"name" : "roscpp_generate_messages_nodejs",
					"projectIndex" : 4
				},
				{
					"directoryIndex" : 4,
					"id" : "roscpp_generate_messages_py::@c6794076fdc14014b7f0",
					"jsonFile" : "target-roscpp_generate_messages_py-Debug-bcaaf88b8e488fa60c78.json",
					"name" : "roscpp_generate_messages_py",
					"projectIndex" : 4
				},
				{
					"directoryIndex" : 4,
					"id" : "rosgraph_msgs_generate_messages_cpp::@c6794076fdc14014b7f0",
					"jsonFile" : "target-rosgraph_msgs_generate_messages_cpp-Debug-8341fdb4f975dc5c3b6c.json",
					"name" : "rosgraph_msgs_generate_messages_cpp",
					"projectIndex" : 4
				},
				{
					"directoryIndex" : 4,
					"id" : "rosgraph_msgs_generate_messages_eus::@c6794076fdc14014b7f0",
					"jsonFile" : "target-rosgraph_msgs_generate_messages_eus-Debug-267cd326c7e722a4bf73.json",
					"name" : "rosgraph_msgs_generate_messages_eus",
					"projectIndex" : 4
				},
				{
					"directoryIndex" : 4,
					"id" : "rosgraph_msgs_generate_messages_lisp::@c6794076fdc14014b7f0",
					"jsonFile" : "target-rosgraph_msgs_generate_messages_lisp-Debug-2c9a34ff8a278786540e.json",
					"name" : "rosgraph_msgs_generate_messages_lisp",
					"projectIndex" : 4
				},
				{
					"directoryIndex" : 4,
					"id" : "rosgraph_msgs_generate_messages_nodejs::@c6794076fdc14014b7f0",
					"jsonFile" : "target-rosgraph_msgs_generate_messages_nodejs-Debug-f6203db1cb19dbbe803b.json",
					"name" : "rosgraph_msgs_generate_messages_nodejs",
					"projectIndex" : 4
				},
				{
					"directoryIndex" : 4,
					"id" : "rosgraph_msgs_generate_messages_py::@c6794076fdc14014b7f0",
					"jsonFile" : "target-rosgraph_msgs_generate_messages_py-Debug-58897d6a1033e19d73bf.json",
					"name" : "rosgraph_msgs_generate_messages_py",
					"projectIndex" : 4
				},
				{
					"directoryIndex" : 0,
					"id" : "run_tests::@6890427a1f51a3e7e1df",
					"jsonFile" : "target-run_tests-Debug-8df51f7a33fa18f9de57.json",
					"name" : "run_tests",
					"projectIndex" : 0
				},
				{
					"directoryIndex" : 4,
					"id" : "std_msgs_generate_messages_cpp::@c6794076fdc14014b7f0",
					"jsonFile" : "target-std_msgs_generate_messages_cpp-Debug-0216e3a590e7bf8dcdfe.json",
					"name" : "std_msgs_generate_messages_cpp",
					"projectIndex" : 4
				},
				{
					"directoryIndex" : 4,
					"id" : "std_msgs_generate_messages_eus::@c6794076fdc14014b7f0",
					"jsonFile" : "target-std_msgs_generate_messages_eus-Debug-f21ba2abcadba5d13585.json",
					"name" : "std_msgs_generate_messages_eus",
					"projectIndex" : 4
				},
				{
					"directoryIndex" : 4,
					"id" : "std_msgs_generate_messages_lisp::@c6794076fdc14014b7f0",
					"jsonFile" : "target-std_msgs_generate_messages_lisp-Debug-dd08960ff2bfe30654f7.json",
					"name" : "std_msgs_generate_messages_lisp",
					"projectIndex" : 4
				},
				{
					"directoryIndex" : 4,
					"id" : "std_msgs_generate_messages_nodejs::@c6794076fdc14014b7f0",
					"jsonFile" : "target-std_msgs_generate_messages_nodejs-Debug-d3e18c03e29940b51b0b.json",
					"name" : "std_msgs_generate_messages_nodejs",
					"projectIndex" : 4
				},
				{
					"directoryIndex" : 4,
					"id" : "std_msgs_generate_messages_py::@c6794076fdc14014b7f0",
					"jsonFile" : "target-std_msgs_generate_messages_py-Debug-2e6ac0959bf7560fb52a.json",
					"name" : "std_msgs_generate_messages_py",
					"projectIndex" : 4
				},
				{
					"directoryIndex" : 4,
					"id" : "sub_01_c::@c6794076fdc14014b7f0",
					"jsonFile" : "target-sub_01_c-Debug-871a8c50a0b09fddeaa3.json",
					"name" : "sub_01_c",
					"projectIndex" : 4
				},
				{
					"directoryIndex" : 0,
					"id" : "tests::@6890427a1f51a3e7e1df",
					"jsonFile" : "target-tests-Debug-645674a8b6faee116c67.json",
					"name" : "tests",
					"projectIndex" : 0
				}
			]
		}
	],
	"kind" : "codemodel",
	"paths" : 
	{
		"build" : "/home/k/test/demo_03_ws/src/build",
		"source" : "/home/k/test/demo_03_ws/src"
	},
	"version" : 
	{
		"major" : 2,
		"minor" : 0
	}
}
